my_app/__init__.py
my_app/_version.py
my_app/my_app.py
pixegami_my_app-1.0.1.dist-info/METADATA
pixegami_my_app-1.0.1.dist-info/WHEEL
pixegami_my_app-1.0.1.dist-info/entry_points.txt
pixegami_my_app-1.0.1.dist-info/top_level.txt
pixegami_my_app-1.0.1.dist-info/RECORD
