Metadata-Version: 2.1
Name: pixegami-my-app
Version: 1.0.1
Summary: A template Python CLI app.
Home-page: https://github.com/pixegami/python-cli-template
Author: Pixegami
Author-email: pixegami@gmail.com
License: UNKNOWN
Platform: UNKNOWN
Classifier: Programming Language :: Python :: 3.8
